[{"avg_throughput":0,"avg_latency":0},{"avg_throughput":0,"avg_latency":0},{"avg_throughput":0,"avg_latency":0},{"avg_throughput":0,"avg_latency":0},{"avg_throughput":0,"avg_latency":0},{"avg_throughput":0,"avg_latency":0},{"avg_throughput":0,"avg_latency":0},{"avg_throughput":0,"avg_latency":0},{"avg_throughput":2.5618113121860127,"avg_latency":0.054256598154703774},{"avg_throughput":0,"avg_latency":0},{"avg_throughput":87.9136559866491,"avg_latency":0.15495919802285343},{"avg_throughput":0,"avg_latency":0},{"avg_throughput":82.77404342059941,"avg_latency":0.15183650154665293},{"avg_throughput":0,"avg_latency":0},{"avg_throughput":97.12287225865845,"avg_latency":0.18021352393458587},{"avg_throughput":0,"avg_latency":0},{"avg_throughput":76.42363750713537,"avg_latency":0.11326239759625953},{"avg_throughput":0,"avg_latency":0},{"avg_throughput":79.17009038491317,"avg_latency":0.1477233186746255},{"avg_throughput":0,"avg_latency":0},{"avg_throughput":101.94901539863041,"avg_latency":0.09988252907991409},{"avg_throughput":0,"avg_latency":0},{"avg_throughput":31.541188060108976,"avg_latency":0.09378385378254785},{"avg_throughput":0,"avg_latency":0},{"avg_throughput":65.9548967421026,"avg_latency":0.14059909500859},{"avg_throughput":0,"avg_latency":0},{"avg_throughput":74.83331130875816,"avg_latency":0.08741450749787709},{"avg_throughput":7458.685949701894,"avg_latency":0.22562472219578922},{"avg_throughput":83.17212301189771,"avg_latency":0.36725808224992124},{"avg_throughput":0,"avg_latency":0},{"avg_throughput":85.57901938649923,"avg_latency":0.15335391069713392},{"avg_throughput":0,"avg_latency":0},{"avg_throughput":101.17391437529314,"avg_latency":0.22618077317280555},{"avg_throughput":0,"avg_latency":0},{"avg_throughput":152.01583224935115,"avg_latency":0.5085479651506131},{"avg_throughput":0,"avg_latency":0},{"avg_throughput":69.15476568215888,"avg_latency":0.18835893495758968},{"avg_throughput":0,"avg_latency":0},{"avg_throughput":142.07203052215172,"avg_latency":0.27908008283292746},{"avg_throughput":0,"avg_latency":0},{"avg_throughput":44.85170006945726,"avg_latency":0.10719992105777447},{"avg_throughput":0,"avg_latency":0},{"avg_throughput":133.18879130529564,"avg_latency":0.312862423312573},{"avg_throughput":0,"avg_latency":0},{"avg_throughput":117.9634669664331,"avg_latency":0.25086107318332085},{"avg_throughput":0,"avg_latency":0},{"avg_throughput":120.42893489116703,"avg_latency":0.23075825569540634},{"avg_throughput":0,"avg_latency":0},{"avg_throughput":81.50694580340017,"avg_latency":0.14049354535114916},{"avg_throughput":0,"avg_latency":0},{"avg_throughput":150.57954426515056,"avg_latency":0.40038797140910926},{"avg_throughput":0,"avg_latency":0},{"avg_throughput":126.46660958932996,"avg_latency":0.42626562655209543},{"avg_throughput":0,"avg_latency":0},{"avg_throughput":52.299849210544956,"avg_latency":0.15788708557592374},{"avg_throughput":0,"avg_latency":0},{"avg_throughput":50.17602502195339,"avg_latency":0.18341237604618071},{"avg_throughput":0,"avg_latency":0},{"avg_throughput":62.569557344229494,"avg_latency":0.13164414245574202},{"avg_throughput":0,"avg_latency":0},{"avg_throughput":144.22202980978165,"avg_latency":0.5035679837067922},{"avg_throughput":0,"avg_latency":0},{"avg_throughput":0,"avg_latency":0},{"avg_throughput":0,"avg_latency":0},{"avg_throughput":0,"avg_latency":0},{"avg_throughput":0,"avg_latency":0},{"avg_throughput":0.20793429802943392,"avg_latency":0.06403252979119618},{"avg_throughput":0,"avg_latency":0},{"avg_throughput":75.01944763709908,"avg_latency":0.14183934570169773},{"avg_throughput":0,"avg_latency":0},{"avg_throughput":95.68830968937097,"avg_latency":0.19049800901363292},{"avg_throughput":0,"avg_latency":0},{"avg_throughput":96.63170665412949,"avg_latency":0.19029980867800086},{"avg_throughput":0,"avg_latency":0},{"avg_throughput":76.58515886945929,"avg_latency":0.11408610768567502},{"avg_throughput":0,"avg_latency":0},{"avg_throughput":79.99671398190141,"avg_latency":0.1546195367207894},{"avg_throughput":0,"avg_latency":0},{"avg_throughput":101.76481561253125,"avg_latency":0.10977649629116058},{"avg_throughput":0,"avg_latency":0},{"avg_throughput":31.567273016963302,"avg_latency":0.09579945698616997},{"avg_throughput":0,"avg_latency":0},{"avg_throughput":66.08741051360731,"avg_latency":0.14059212916728223},{"avg_throughput":0,"avg_latency":0},{"avg_throughput":81.97915618850806,"avg_latency":0.10768210986701164},{"avg_throughput":0,"avg_latency":0},{"avg_throughput":83.07550605485096,"avg_latency":0.36373924227321847},{"avg_throughput":0,"avg_latency":0},{"avg_throughput":101.336953899315,"avg_latency":0.17547564494786005},{"avg_throughput":0,"avg_latency":0},{"avg_throughput":102.32904012545194,"avg_latency":0.31981002407025566},{"avg_throughput":0,"avg_latency":0},{"avg_throughput":141.13812073207188,"avg_latency":0.6440529350284155},{"avg_throughput":0,"avg_latency":0},{"avg_throughput":82.8417101976268,"avg_latency":0.21174856302249861},{"avg_throughput":0,"avg_latency":0},{"avg_throughput":139.23480471507744,"avg_latency":0.26590866108663674},{"avg_throughput":0,"avg_latency":0},{"avg_throughput":42.310803010899974,"avg_latency":0.11786425569478204},{"avg_throughput":0,"avg_latency":0},{"avg_throughput":140.44217741843292,"avg_latency":0.3566802308550872},{"avg_throughput":0,"avg_latency":0},{"avg_throughput":110.51609127426457,"avg_latency":0.3515901923179626},{"avg_throughput":0,"avg_latency":0},{"avg_throughput":119.85730713735894,"avg_latency":0.28837273551220716},{"avg_throughput":0,"avg_latency":0},{"avg_throughput":82.41909001794656,"avg_latency":0.15004192085205753},{"avg_throughput":0,"avg_latency":0},{"avg_throughput":128.67516503516933,"avg_latency":0.4424573874566704},{"avg_throughput":0,"avg_latency":0},{"avg_throughput":152.44940204862607,"avg_latency":0.6032291625366837},{"avg_throughput":0,"avg_latency":0},{"avg_throughput":48.62968426331414,"avg_latency":0.16575581076169255},{"avg_throughput":0,"avg_latency":0},{"avg_throughput":49.62270122986736,"avg_latency":0.1765475070476532},{"avg_throughput":0,"avg_latency":0},{"avg_throughput":56.54835091707279,"avg_latency":0.125122324042364},{"avg_throughput":0,"avg_latency":0},{"avg_throughput":144.5468859149748,"avg_latency":0.5425187668038739},{"avg_throughput":0,"avg_latency":0}]